README.md
setup.py
NCP_OAuth/OAuth.py
NCP_OAuth/__init__.py
NCP_OAuth.egg-info/PKG-INFO
NCP_OAuth.egg-info/SOURCES.txt
NCP_OAuth.egg-info/dependency_links.txt
NCP_OAuth.egg-info/requires.txt
NCP_OAuth.egg-info/top_level.txt