Metadata-Version: 1.2
Name: NCP-OAuth
Version: 0.14
Summary: This is for OAuth of NAVER Cloud Platform	https://github.com/ultimatelife/NCP_OAuth.git
Home-page: https://github.com/ultimatelife/NCP_OAuth.git
Author: geonwoo.kim
Author-email: drama0708@gmail.com
License: Naver Cloud Platform
Keywords: NCP,naver cloud platform,ncp-oauth,ncp
Platform: UNKNOWN
Classifier: Programming Language :: Python :: 3.6
Requires-Python: >=3.6
